django_madval/__init__.py
django_madval/admin.py
django_madval/apps.py
django_madval/models.py
django_madval/tests.py
django_madval/views.py
django_madval/migrations/__init__.py
django_madval/templatetags/__init__.py
django_madval/templatetags/madval_check_english.py
django_madval/templatetags/madval_fat_and_sugar_color.py
django_madval/templatetags/madval_get_items_count.py
django_madval/templatetags/madval_make_for_loop.py
django_madval/templatetags/madval_math.py
django_madval/templatetags/madval_persian_translation.py
django_madval-0.0.3.dist-info/LICENSE
django_madval-0.0.3.dist-info/METADATA
django_madval-0.0.3.dist-info/WHEEL
django_madval-0.0.3.dist-info/top_level.txt
django_madval-0.0.3.dist-info/RECORD
