Metadata-Version: 2.1
Name: django_madval
Version: 0.0.3
Summary: A django package to use either persian numbers or comma separated persian numbers in djanog. You can also translate weekdays to persian and use persian name for months!
Author-email: Mohammad Pourmohammadi Fallah <mohammad.pfallah@gmail.com>
Project-URL: Homepage, https://github.com/pypa/sampleproject
Project-URL: Issues, https://github.com/pypa/sampleproject/issues
Project-URL: Sourcecode, https://github.com/mohammadpmf/django_madval
Classifier: Programming Language :: Python :: 3
Classifier: License :: OSI Approved :: MIT License
Classifier: Operating System :: OS Independent
Requires-Python: >=3.9
License-File: LICENSE
